mylib_09/__init__.py
mylib_09-0.1.dist-info/LICENSE.txt
mylib_09-0.1.dist-info/METADATA
mylib_09-0.1.dist-info/WHEEL
mylib_09-0.1.dist-info/top_level.txt
mylib_09-0.1.dist-info/RECORD
