Metadata-Version: 2.1
Name: mylib-09
Version: 0.1
Summary: for printing pattern
Author: ANKUR
Author-email: vy8655@gmail.com
Classifier: Programming Language :: Python :: 3
Classifier: License :: OSI Approved :: MIT License
Classifier: Operating System :: OS Independent
License-File: LICENSE.txt
